echo_pdm_demo-0.1.0.dist-info/METADATA
echo_pdm_demo-0.1.0.dist-info/WHEEL
pdm_demo/__init__.py
echo_pdm_demo-0.1.0.dist-info/RECORD
