Metadata-Version: 2.1
Name: echo_pdm_demo
Version: 0.1.0
Summary: desc
Author-Email: mh-swift <zuojiadazhongma@gmail.com>
License: MIT
Requires-Python: >=3.8
Requires-Dist: requests>=2.31.0
Requires-Dist: faker>=22.0.0
